README.md
setup.py
graphsite/__init__.py
graphsite/graphsite.py
graphsite/version.py
graphsite.egg-info/PKG-INFO
graphsite.egg-info/SOURCES.txt
graphsite.egg-info/dependency_links.txt
graphsite.egg-info/requires.txt
graphsite.egg-info/top_level.txt