Metadata-Version: 2.1
Name: graphsite
Version: 0.1.0
Summary: Compute graph representations of protein binding sites
Home-page: https://github.com/shiwentao00/Graphsite
Author: Wentao Shi
Author-email: wentao771@gmail.com
License: UNKNOWN
Platform: UNKNOWN
Requires-Python: >=3.7
